google_play_scraper/__init__.py
google_play_scraper/exceptions.py
google_play_scraper/constants/__init__.py
google_play_scraper/constants/element.py
google_play_scraper/constants/google_play.py
google_play_scraper/constants/regex.py
google_play_scraper/constants/request.py
google_play_scraper/features/__init__.py
google_play_scraper/features/app.py
google_play_scraper/features/reviews.py
google_play_scraper/utils/__init__.py
google_play_scraper/utils/data_processors.py
google_play_scraper/utils/request.py
tests/e2e_tests/__init__.py
tests/e2e_tests/test_app.py
tests/e2e_tests/test_reviews.py
tests/e2e_tests/test_reviews_all.py
async_google_play_scraper-0.1.3.dist-info/LICENSE
async_google_play_scraper-0.1.3.dist-info/METADATA
async_google_play_scraper-0.1.3.dist-info/WHEEL
async_google_play_scraper-0.1.3.dist-info/top_level.txt
async_google_play_scraper-0.1.3.dist-info/RECORD
