Metadata-Version: 2.1
Name: async-google-play-scraper
Version: 0.1.3
Summary: Async-Google-Play-Scraper provides APIs to easily crawl the Google Play Store for Python with aiohttp!
Home-page: https://github.com/liorchen/google-play-scraper
Author: Lior Chen
Author-email: liorchen2@gmail.com
License: MIT
Platform: UNKNOWN
Classifier: Topic :: Software Development :: Libraries :: Python Modules
Classifier: Topic :: Utilities
Classifier: Development Status :: 5 - Production/Stable
Classifier: Operating System :: MacOS
Classifier: Operating System :: Microsoft
Classifier: Programming Language :: Python
Classifier: Programming Language :: Python :: 3
Classifier: Programming Language :: Python :: 3.3
Classifier: Programming Language :: Python :: 3.4
Classifier: Programming Language :: Python :: 3.5
Classifier: Programming Language :: Python :: 3.6
Classifier: Programming Language :: Python :: 3.7
Classifier: Programming Language :: Python :: 3.8
Classifier: Typing :: Typed
Requires-Python: >=3.3
Requires-Dist: aiohttp (<4.0,>=3.5.2)
